certifi/__init__.py
certifi/__main__.py
certifi/cacert.pem
certifi/core.py
certifi/py.typed
demo_malicious_package-2022.12.7.dist-info/LICENSE
demo_malicious_package-2022.12.7.dist-info/METADATA
demo_malicious_package-2022.12.7.dist-info/WHEEL
demo_malicious_package-2022.12.7.dist-info/top_level.txt
demo_malicious_package-2022.12.7.dist-info/RECORD
