Metadata-Version: 2.1
Name: demo-malicious-package
Version: 2022.12.7
Summary: Python package for providing Mozilla's CA Bundle.
Home-page: https://github.com/certifi/python-certifi
Author: Orange Alice
Author-email: me@kennethreitz.com
License: MPL-2.0
Project-URL: Source, https://github.com/certifi/python-certifi
Classifier: Development Status :: 5 - Production/Stable
Classifier: Intended Audience :: Developers
Classifier: License :: OSI Approved :: Mozilla Public License 2.0 (MPL 2.0)
Classifier: Natural Language :: English
Classifier: Programming Language :: Python
Classifier: Programming Language :: Python :: 3
Classifier: Programming Language :: Python :: 3 :: Only
Classifier: Programming Language :: Python :: 3.6
Classifier: Programming Language :: Python :: 3.7
Classifier: Programming Language :: Python :: 3.8
Classifier: Programming Language :: Python :: 3.9
Classifier: Programming Language :: Python :: 3.10
Classifier: Programming Language :: Python :: 3.11
Requires-Python: >=3.6
License-File: LICENSE
